troy_playground/__init__.py
troy_playground/core.py
troy_playground-0.1.0.dist-info/licenses/LICENSE
troy_playground-0.1.0.dist-info/METADATA
troy_playground-0.1.0.dist-info/WHEEL
troy_playground-0.1.0.dist-info/top_level.txt
troy_playground-0.1.0.dist-info/RECORD
