Metadata-Version: 2.4
Name: troy-playground
Version: 0.1.0
Summary: Execute functions and extract their local variables for debugging and testing
Author-email: Sisung Kim <sisung.kim1@gmail.com>
Project-URL: Homepage, https://github.com/crimson206/troy-playground
Project-URL: Repository, https://github.com/crimson206/troy-playground
Requires-Python: >=3.10
License-File: LICENSE
Dynamic: license-file
